pysphorb/__init__.py
pysphorb/pysphorb.cpython-311-x86_64-linux-gnu.so
pysphorb/src/Data/geoinfo102.pfm
pysphorb/src/Data/geoinfo128.pfm
pysphorb/src/Data/geoinfo162.pfm
pysphorb/src/Data/geoinfo204.pfm
pysphorb/src/Data/geoinfo256.pfm
pysphorb/src/Data/geoinfo64.pfm
pysphorb/src/Data/geoinfo80.pfm
pysphorb/src/Data/imginfo102_0.pfm
pysphorb/src/Data/imginfo102_1.pfm
pysphorb/src/Data/imginfo102_2.pfm
pysphorb/src/Data/imginfo102_3.pfm
pysphorb/src/Data/imginfo102_4.pfm
pysphorb/src/Data/imginfo128_0.pfm
pysphorb/src/Data/imginfo128_1.pfm
pysphorb/src/Data/imginfo128_2.pfm
pysphorb/src/Data/imginfo128_3.pfm
pysphorb/src/Data/imginfo128_4.pfm
pysphorb/src/Data/imginfo162_0.pfm
pysphorb/src/Data/imginfo162_1.pfm
pysphorb/src/Data/imginfo162_2.pfm
pysphorb/src/Data/imginfo162_3.pfm
pysphorb/src/Data/imginfo162_4.pfm
pysphorb/src/Data/imginfo204_0.pfm
pysphorb/src/Data/imginfo204_1.pfm
pysphorb/src/Data/imginfo204_2.pfm
pysphorb/src/Data/imginfo204_3.pfm
pysphorb/src/Data/imginfo204_4.pfm
pysphorb/src/Data/imginfo256_0.pfm
pysphorb/src/Data/imginfo256_1.pfm
pysphorb/src/Data/imginfo256_2.pfm
pysphorb/src/Data/imginfo256_3.pfm
pysphorb/src/Data/imginfo256_4.pfm
pysphorb/src/Data/imginfo64_0.pfm
pysphorb/src/Data/imginfo64_1.pfm
pysphorb/src/Data/imginfo64_2.pfm
pysphorb/src/Data/imginfo64_3.pfm
pysphorb/src/Data/imginfo64_4.pfm
pysphorb/src/Data/imginfo80_0.pfm
pysphorb/src/Data/imginfo80_1.pfm
pysphorb/src/Data/imginfo80_2.pfm
pysphorb/src/Data/imginfo80_3.pfm
pysphorb/src/Data/imginfo80_4.pfm
pysphorb/src/Data/mask102.bmp
pysphorb/src/Data/mask128.bmp
pysphorb/src/Data/mask162.bmp
pysphorb/src/Data/mask204.bmp
pysphorb/src/Data/mask256.bmp
pysphorb/src/Data/mask64.bmp
pysphorb/src/Data/mask80.bmp
pysphorb.libs/libHalf-2_5-da60cc87.so.25.0.6
pysphorb.libs/libIex-2_5-c16c5aa2.so.25.0.6
pysphorb.libs/libIlmImf-2_5-7155da24.so.25.0.6
pysphorb.libs/libIlmThread-2_5-8f344396.so.25.0.6
pysphorb-0.1.5.dist-info/METADATA
pysphorb-0.1.5.dist-info/WHEEL
pysphorb-0.1.5.dist-info/RECORD
