Metadata-Version: 2.2
Name: pysphorb
Version: 0.1.5
Summary: Python bindings for SPHORB feature detector
Keywords: sphorb,feature-detection,computer-vision,panoramic,spherical
Author-Email: Sehyun Cha <cshyundev@gmail.com>
License: GPL
Classifier: Development Status :: 4 - Beta
Classifier: Intended Audience :: Developers
Classifier: Intended Audience :: Science/Research
Classifier: License :: OSI Approved :: GNU General Public License (GPL)
Classifier: Programming Language :: Python :: 3
Classifier: Programming Language :: Python :: 3.11
Classifier: Programming Language :: Python :: 3.12
Classifier: Programming Language :: C++
Classifier: Topic :: Scientific/Engineering :: Image Recognition
Project-URL: Homepage, https://github.com/cshyundev/py_sphorb
Project-URL: Repository, https://github.com/cshyundev/py_sphorb
Project-URL: Issues, https://github.com/cshyundev/py_sphorb/issues
Requires-Python: >=3.11
Requires-Dist: numpy>=2.0.0
Requires-Dist: opencv-python>=4.0.0
Provides-Extra: dev
Requires-Dist: pytest>=7.0; extra == "dev"
